LICENSE.txt
README.md
setup.py
Topsis_Shivam_102116113/topsis-102116113.py
Topsis_Shivam_102116113.egg-info/PKG-INFO
Topsis_Shivam_102116113.egg-info/SOURCES.txt
Topsis_Shivam_102116113.egg-info/dependency_links.txt
Topsis_Shivam_102116113.egg-info/entry_points.txt
Topsis_Shivam_102116113.egg-info/requires.txt
Topsis_Shivam_102116113.egg-info/top_level.txt