Metadata-Version: 2.1
Name: Topsis_Shivam_102116113
Version: 1.0.0
Summary: Calculates Topsis Score and Rank
Home-page: https://github.com/shiivvvaam/Topsis_Shivam_102116113.git
Author: Shivam Dhiman
Author-email: shivam4968@gmail.com
License: MIT
Classifier: Programming Language :: Python :: 3
Classifier: License :: OSI Approved :: MIT License
Classifier: Operating System :: OS Independent
License-File: LICENSE.txt
Requires-Dist: pandas
